<?xml version="1.0" encoding="UTF-8"?>
<!DOCTYPE plist PUBLIC "-//Apple//DTD PLIST 1.0//EN" "http://www.apple.com/DTDs/PropertyList-1.0.dtd"/>

<plist version="1.0">
    <dict>
        <key>ROOT</key>
        <array>
            <dict>
                <key>id</key>
                <string>639</string>
                <key>className</key>
                <string>PTModelAssetObstacle</string>
                <key>Name</key>
                <dict>
                    <key>value</key>
                    <string>TriangleTrail</string>
                </dict>
                <key>Collision Shape</key>
                <dict>
                    <key>id</key>
                    <string>640</string>
                    <key>className</key>
                    <string>PTModelPolygon</string>
                    <key>points</key>
                    <array>
                        <string>{0.000000,-62.000000}</string>
                        <string>{73.000000,63.000000}</string>
                        <string>{-70.000000,63.000000}</string>
                    </array>
                    <key>oneWayCollisionVector</key>
                    <string>{0.000000,0.000000}</string>
                    <key>shapeType</key>
                    <string>1</string>
                </dict>
            </dict>
            <dict>
                <key>id</key>
                <string>811</string>
                <key>className</key>
                <string>PTModelAssetObstacle</string>
                <key>Name</key>
                <dict>
                    <key>value</key>
                    <string>BlackBlock</string>
                </dict>
                <key>Collision Shape</key>
                <dict>
                    <key>id</key>
                    <string>862</string>
                    <key>className</key>
                    <string>PTModelPolygon</string>
                    <key>points</key>
                    <array>
                        <string>{-50.000000,-50.000000}</string>
                        <string>{50.000000,-50.000000}</string>
                        <string>{50.000000,50.000000}</string>
                        <string>{-50.000000,50.000000}</string>
                    </array>
                    <key>oneWayCollisionVector</key>
                    <string>{0.000000,0.000000}</string>
                    <key>shapeType</key>
                    <string>1</string>
                </dict>
                <key>Health</key>
                <dict>
                    <key>value</key>
                    <string>0.000000</string>
                    <key>useDefault</key>
                    <string>0</string>
                </dict>
            </dict>
            <dict>
                <key>id</key>
                <string>1117</string>
                <key>className</key>
                <string>PTModelAssetObstacle</string>
                <key>Name</key>
                <dict>
                    <key>value</key>
                    <string>TriangleSymmetrical</string>
                </dict>
                <key>Collision Shape</key>
                <dict>
                    <key>id</key>
                    <string>1118</string>
                    <key>className</key>
                    <string>PTModelPolygon</string>
                    <key>points</key>
                    <array>
                        <string>{1.000000,-180.000000}</string>
                        <string>{250.000000,251.000000}</string>
                        <string>{-250.000000,251.000000}</string>
                    </array>
                    <key>oneWayCollisionVector</key>
                    <string>{0.000000,0.000000}</string>
                    <key>shapeType</key>
                    <string>1</string>
                </dict>
                <key>Health</key>
                <dict>
                    <key>value</key>
                    <string>0.000000</string>
                    <key>useDefault</key>
                    <string>0</string>
                </dict>
            </dict>
            <dict>
                <key>id</key>
                <string>1175</string>
                <key>className</key>
                <string>PTModelAssetObstacle</string>
                <key>Name</key>
                <dict>
                    <key>value</key>
                    <string>TriangleSymmetricalBlack</string>
                </dict>
                <key>Collision Shape</key>
                <dict>
                    <key>id</key>
                    <string>2339</string>
                    <key>className</key>
                    <string>PTModelPolygon</string>
                    <key>points</key>
                    <array>
                        <string>{-1.000000,-213.000000}</string>
                        <string>{250.000000,216.000000}</string>
                        <string>{-250.000000,216.000000}</string>
                    </array>
                    <key>oneWayCollisionVector</key>
                    <string>{0.000000,0.000000}</string>
                    <key>shapeType</key>
                    <string>1</string>
                </dict>
                <key>Health</key>
                <dict>
                    <key>value</key>
                    <string>0.000000</string>
                    <key>useDefault</key>
                    <string>0</string>
                </dict>
            </dict>
            <dict>
                <key>id</key>
                <string>1333</string>
                <key>className</key>
                <string>PTModelAssetObstacle</string>
                <key>Name</key>
                <dict>
                    <key>value</key>
                    <string>Trail</string>
                </dict>
                <key>Collision Shape</key>
                <dict>
                    <key>id</key>
                    <string>1334</string>
                    <key>className</key>
                    <string>PTModelPolygon</string>
                    <key>points</key>
                    <array>
                        <string>{-103.000000,150.000000}</string>
                        <string>{-144.250000,1.875000}</string>
                        <string>{-103.500000,-150.250000}</string>
                        <string>{-1.000000,-231.500000}</string>
                        <string>{108.000000,-150.000000}</string>
                        <string>{140.000000,-3.000000}</string>
                        <string>{105.000000,151.000000}</string>
                        <string>{1.000000,228.000000}</string>
                    </array>
                    <key>oneWayCollisionVector</key>
                    <string>{0.000000,0.000000}</string>
                    <key>shapeType</key>
                    <string>1</string>
                </dict>
            </dict>
            <dict>
                <key>id</key>
                <string>1721</string>
                <key>className</key>
                <string>PTModelAssetObstacle</string>
                <key>Name</key>
                <dict>
                    <key>value</key>
                    <string>BlueCube</string>
                </dict>
                <key>Collision Shape</key>
                <dict>
                    <key>id</key>
                    <string>1722</string>
                    <key>className</key>
                    <string>PTModelPolygon</string>
                    <key>points</key>
                    <array>
                        <string>{-50.000000,-50.000000}</string>
                        <string>{50.000000,-50.000000}</string>
                        <string>{50.000000,50.000000}</string>
                        <string>{-50.000000,50.000000}</string>
                    </array>
                    <key>oneWayCollisionVector</key>
                    <string>{0.000000,0.000000}</string>
                    <key>shapeType</key>
                    <string>1</string>
                </dict>
            </dict>
            <dict>
                <key>id</key>
                <string>2521</string>
                <key>className</key>
                <string>PTModelAssetObstacle</string>
                <key>Name</key>
                <dict>
                    <key>value</key>
                    <string>WhiteBlock</string>
                </dict>
                <key>Collision Shape</key>
                <dict>
                    <key>id</key>
                    <string>2522</string>
                    <key>className</key>
                    <string>PTModelPolygon</string>
                    <key>points</key>
                    <array>
                        <string>{-50.000000,-50.000000}</string>
                        <string>{50.000000,-50.000000}</string>
                        <string>{50.000000,50.000000}</string>
                        <string>{-50.000000,50.000000}</string>
                    </array>
                    <key>oneWayCollisionVector</key>
                    <string>{0.000000,0.000000}</string>
                    <key>shapeType</key>
                    <string>1</string>
                </dict>
                <key>Health</key>
                <dict>
                    <key>value</key>
                    <string>0.000000</string>
                    <key>useDefault</key>
                    <string>0</string>
                </dict>
            </dict>
            <dict>
                <key>id</key>
                <string>2677</string>
                <key>className</key>
                <string>PTModelAssetObstacle</string>
                <key>Name</key>
                <dict>
                    <key>value</key>
                    <string>Walls</string>
                </dict>
                <key>Collision Shape</key>
                <dict>
                    <key>id</key>
                    <string>2678</string>
                    <key>className</key>
                    <string>PTModelPolygon</string>
                    <key>points</key>
                    <array>
                        <string>{-50.000000,-50.000000}</string>
                        <string>{50.000000,-50.000000}</string>
                        <string>{50.000000,50.000000}</string>
                        <string>{-50.000000,50.000000}</string>
                    </array>
                    <key>oneWayCollisionVector</key>
                    <string>{0.000000,0.000000}</string>
                    <key>shapeType</key>
                    <string>1</string>
                </dict>
            </dict>
            <dict>
                <key>id</key>
                <string>3710</string>
                <key>className</key>
                <string>PTModelAssetObstacle</string>
                <key>Name</key>
                <dict>
                    <key>value</key>
                    <string>WhiteCircle</string>
                </dict>
                <key>Collision Shape</key>
                <dict>
                    <key>id</key>
                    <string>3726</string>
                    <key>className</key>
                    <string>PTModelCircle</string>
                    <key>points</key>
                    <array>
                        <string>{0.000000,0.000000}</string>
                        <string>{497.000000,0.000000}</string>
                    </array>
                    <key>oneWayCollisionVector</key>
                    <string>{0.000000,0.000000}</string>
                    <key>shapeType</key>
                    <string>2</string>
                </dict>
                <key>Health</key>
                <dict>
                    <key>value</key>
                    <string>0.000000</string>
                    <key>useDefault</key>
                    <string>0</string>
                </dict>
            </dict>
            <dict>
                <key>id</key>
                <string>6910</string>
                <key>className</key>
                <string>PTModelAssetObstacle</string>
                <key>Name</key>
                <dict>
                    <key>value</key>
                    <string>BlockHalfBlack</string>
                </dict>
                <key>Collision Shape</key>
                <dict>
                    <key>id</key>
                    <string>6911</string>
                    <key>className</key>
                    <string>PTModelPolygon</string>
                    <key>points</key>
                    <array>
                        <string>{-50.000000,-50.000000}</string>
                        <string>{50.000000,-50.000000}</string>
                        <string>{50.000000,50.000000}</string>
                        <string>{-50.000000,50.000000}</string>
                    </array>
                    <key>oneWayCollisionVector</key>
                    <string>{0.000000,0.000000}</string>
                    <key>shapeType</key>
                    <string>1</string>
                </dict>
                <key>Health</key>
                <dict>
                    <key>value</key>
                    <string>0.000000</string>
                    <key>useDefault</key>
                    <string>0</string>
                </dict>
            </dict>
            <dict>
                <key>id</key>
                <string>10690</string>
                <key>className</key>
                <string>PTModelAssetObstacle</string>
                <key>Name</key>
                <dict>
                    <key>value</key>
                    <string>SwipeControl</string>
                </dict>
                <key>Collision Shape</key>
                <dict>
                    <key>id</key>
                    <string>10691</string>
                    <key>className</key>
                    <string>PTModelPolygon</string>
                    <key>points</key>
                    <array>
                        <string>{-227.000000,-24.000000}</string>
                        <string>{230.000000,-24.000000}</string>
                        <string>{230.000000,25.000000}</string>
                        <string>{-227.000000,25.000000}</string>
                    </array>
                    <key>oneWayCollisionVector</key>
                    <string>{0.000000,0.000000}</string>
                    <key>shapeType</key>
                    <string>1</string>
                </dict>
            </dict>
            <dict>
                <key>id</key>
                <string>10761</string>
                <key>className</key>
                <string>PTModelAssetObstacle</string>
                <key>Name</key>
                <dict>
                    <key>value</key>
                    <string>SHADEwhite</string>
                </dict>
                <key>Collision Shape</key>
                <dict>
                    <key>id</key>
                    <string>10762</string>
                    <key>className</key>
                    <string>PTModelPolygon</string>
                    <key>points</key>
                    <array>
                        <string>{-246.000000,-53.000000}</string>
                        <string>{247.000000,-53.000000}</string>
                        <string>{247.000000,52.000000}</string>
                        <string>{-246.000000,52.000000}</string>
                    </array>
                    <key>oneWayCollisionVector</key>
                    <string>{0.000000,0.000000}</string>
                    <key>shapeType</key>
                    <string>1</string>
                </dict>
            </dict>
            <dict>
                <key>id</key>
                <string>11681</string>
                <key>className</key>
                <string>PTModelAssetObstacle</string>
                <key>Name</key>
                <dict>
                    <key>value</key>
                    <string>InvisibleObject</string>
                </dict>
                <key>Collision Shape</key>
                <dict>
                    <key>id</key>
                    <string>11682</string>
                    <key>className</key>
                    <string>PTModelPolygon</string>
                    <key>points</key>
                    <array>
                        <string>{-50.000000,-50.000000}</string>
                        <string>{50.000000,-50.000000}</string>
                        <string>{50.000000,50.000000}</string>
                        <string>{-50.000000,50.000000}</string>
                    </array>
                    <key>oneWayCollisionVector</key>
                    <string>{0.000000,0.000000}</string>
                    <key>shapeType</key>
                    <string>1</string>
                </dict>
            </dict>
            <dict>
                <key>id</key>
                <string>8769</string>
                <key>className</key>
                <string>PTModelAssetObstacle</string>
                <key>Name</key>
                <dict>
                    <key>value</key>
                    <string>GreenCube</string>
                </dict>
                <key>Collision Shape</key>
                <dict>
                    <key>id</key>
                    <string>8770</string>
                    <key>className</key>
                    <string>PTModelPolygon</string>
                    <key>points</key>
                    <array>
                        <string>{-50.000000,-50.000000}</string>
                        <string>{50.000000,-50.000000}</string>
                        <string>{50.000000,50.000000}</string>
                        <string>{-50.000000,50.000000}</string>
                    </array>
                    <key>oneWayCollisionVector</key>
                    <string>{0.000000,0.000000}</string>
                    <key>shapeType</key>
                    <string>1</string>
                </dict>
            </dict>
            <dict>
                <key>id</key>
                <string>12047</string>
                <key>className</key>
                <string>PTModelAssetObstacle</string>
                <key>Name</key>
                <dict>
                    <key>value</key>
                    <string>OrangeCube</string>
                </dict>
                <key>Collision Shape</key>
                <dict>
                    <key>id</key>
                    <string>12048</string>
                    <key>className</key>
                    <string>PTModelPolygon</string>
                    <key>points</key>
                    <array>
                        <string>{-80.000000,-80.000000}</string>
                        <string>{80.000000,-80.000000}</string>
                        <string>{80.000000,80.000000}</string>
                        <string>{-80.000000,80.000000}</string>
                    </array>
                    <key>oneWayCollisionVector</key>
                    <string>{0.000000,0.000000}</string>
                    <key>shapeType</key>
                    <string>1</string>
                </dict>
            </dict>
            <dict>
                <key>id</key>
                <string>15522</string>
                <key>className</key>
                <string>PTModelAssetObstacle</string>
                <key>Name</key>
                <dict>
                    <key>value</key>
                    <string>PinkBlock</string>
                </dict>
                <key>Collision Shape</key>
                <dict>
                    <key>id</key>
                    <string>15523</string>
                    <key>className</key>
                    <string>PTModelPolygon</string>
                    <key>points</key>
                    <array>
                        <string>{-50.000000,-50.000000}</string>
                        <string>{50.000000,-50.000000}</string>
                        <string>{50.000000,50.000000}</string>
                        <string>{-50.000000,50.000000}</string>
                    </array>
                    <key>oneWayCollisionVector</key>
                    <string>{0.000000,0.000000}</string>
                    <key>shapeType</key>
                    <string>1</string>
                </dict>
            </dict>
            <dict>
                <key>id</key>
                <string>16532</string>
                <key>className</key>
                <string>PTModelAssetObstacle</string>
                <key>Name</key>
                <dict>
                    <key>value</key>
                    <string>YellowBlock</string>
                </dict>
                <key>Collision Shape</key>
                <dict>
                    <key>id</key>
                    <string>16533</string>
                    <key>className</key>
                    <string>PTModelPolygon</string>
                    <key>points</key>
                    <array>
                        <string>{-50.000000,-50.000000}</string>
                        <string>{50.000000,-50.000000}</string>
                        <string>{50.000000,50.000000}</string>
                        <string>{-50.000000,50.000000}</string>
                    </array>
                    <key>oneWayCollisionVector</key>
                    <string>{0.000000,0.000000}</string>
                    <key>shapeType</key>
                    <string>1</string>
                </dict>
            </dict>
            <dict>
                <key>id</key>
                <string>17424</string>
                <key>className</key>
                <string>PTModelAssetObstacle</string>
                <key>Name</key>
                <dict>
                    <key>value</key>
                    <string>LightSwitch</string>
                </dict>
                <key>Collision Shape</key>
                <dict>
                    <key>id</key>
                    <string>17425</string>
                    <key>className</key>
                    <string>PTModelPolygon</string>
                    <key>points</key>
                    <array>
                        <string>{-50.000000,-12.000000}</string>
                        <string>{50.000000,-12.000000}</string>
                        <string>{50.000000,13.000000}</string>
                        <string>{-50.000000,13.000000}</string>
                    </array>
                    <key>oneWayCollisionVector</key>
                    <string>{0.000000,0.000000}</string>
                    <key>shapeType</key>
                    <string>1</string>
                </dict>
            </dict>
            <dict>
                <key>id</key>
                <string>19528</string>
                <key>className</key>
                <string>PTModelAssetObstacle</string>
                <key>Name</key>
                <dict>
                    <key>value</key>
                    <string>BlackCircle</string>
                </dict>
                <key>Collision Shape</key>
                <dict>
                    <key>id</key>
                    <string>21143</string>
                    <key>className</key>
                    <string>PTModelCircle</string>
                    <key>points</key>
                    <array>
                        <string>{0.000000,0.000000}</string>
                        <string>{495.000000,-8.000000}</string>
                    </array>
                    <key>oneWayCollisionVector</key>
                    <string>{0.000000,0.000000}</string>
                    <key>shapeType</key>
                    <string>2</string>
                </dict>
                <key>Health</key>
                <dict>
                    <key>value</key>
                    <string>0.000000</string>
                    <key>useDefault</key>
                    <string>0</string>
                </dict>
            </dict>
            <dict>
                <key>id</key>
                <string>21165</string>
                <key>className</key>
                <string>PTModelAssetObstacle</string>
                <key>Name</key>
                <dict>
                    <key>value</key>
                    <string>BlackElipse</string>
                </dict>
                <key>Collision Shape</key>
                <dict>
                    <key>id</key>
                    <string>21166</string>
                    <key>className</key>
                    <string>PTModelPolygon</string>
                    <key>points</key>
                    <array>
                        <string>{-500.000000,6.000000}</string>
                        <string>{-346.000000,-354.500000}</string>
                        <string>{1.000000,-500.000000}</string>
                        <string>{353.125000,-348.000000}</string>
                        <string>{495.250000,-3.000000}</string>
                        <string>{352.500000,354.000000}</string>
                        <string>{16.000000,499.000000}</string>
                        <string>{-337.000000,367.000000}</string>
                    </array>
                    <key>oneWayCollisionVector</key>
                    <string>{0.000000,0.000000}</string>
                    <key>shapeType</key>
                    <string>1</string>
                </dict>
                <key>Health</key>
                <dict>
                    <key>value</key>
                    <string>0.000000</string>
                    <key>useDefault</key>
                    <string>0</string>
                </dict>
            </dict>
            <dict>
                <key>id</key>
                <string>21250</string>
                <key>className</key>
                <string>PTModelAssetObstacle</string>
                <key>Name</key>
                <dict>
                    <key>value</key>
                    <string>WhiteElipseRing</string>
                </dict>
                <key>Collision Shape</key>
                <dict>
                    <key>id</key>
                    <string>21251</string>
                    <key>className</key>
                    <string>PTModelPolygon</string>
                    <key>points</key>
                    <array>
                        <string>{-507.000000,-6.000000}</string>
                        <string>{-350.000000,-359.000000}</string>
                        <string>{5.000000,-511.000000}</string>
                        <string>{345.000000,-357.000000}</string>
                        <string>{499.000000,-5.000000}</string>
                        <string>{354.000000,359.000000}</string>
                        <string>{6.000000,503.000000}</string>
                        <string>{-382.000000,342.000000}</string>
                    </array>
                    <key>oneWayCollisionVector</key>
                    <string>{0.000000,0.000000}</string>
                    <key>shapeType</key>
                    <string>1</string>
                </dict>
                <key>Health</key>
                <dict>
                    <key>value</key>
                    <string>0.000000</string>
                    <key>useDefault</key>
                    <string>0</string>
                </dict>
            </dict>
            <dict>
                <key>id</key>
                <string>21450</string>
                <key>className</key>
                <string>PTModelAssetObstacle</string>
                <key>Name</key>
                <dict>
                    <key>value</key>
                    <string>WhiteElipse</string>
                </dict>
                <key>Collision Shape</key>
                <dict>
                    <key>id</key>
                    <string>21451</string>
                    <key>className</key>
                    <string>PTModelPolygon</string>
                    <key>points</key>
                    <array>
                        <string>{-361.000000,-353.000000}</string>
                        <string>{0.000000,-500.000000}</string>
                        <string>{370.000000,-336.000000}</string>
                        <string>{500.000000,0.000000}</string>
                        <string>{346.000000,361.000000}</string>
                        <string>{0.000000,500.000000}</string>
                        <string>{-326.000000,383.000000}</string>
                        <string>{-500.000000,0.000000}</string>
                    </array>
                    <key>oneWayCollisionVector</key>
                    <string>{0.000000,0.000000}</string>
                    <key>shapeType</key>
                    <string>1</string>
                </dict>
                <key>Health</key>
                <dict>
                    <key>value</key>
                    <string>0.000000</string>
                    <key>useDefault</key>
                    <string>0</string>
                </dict>
            </dict>
        </array>
    </dict>
</plist>
